pyArchimate/__init__.py
pyArchimate/checker_rules.yml
pyArchimate/logger.py
pyArchimate/pyArchimate.py
pyArchimate/readers/__init__.py
pyArchimate/readers/archiReader.py
pyArchimate/readers/archimateReader.py
pyArchimate/readers/arisAMLreader.py
pyArchimate/writers/__init__.py
pyArchimate/writers/archiWriter.py
pyArchimate/writers/archimateWriter.py
pyArchimate/writers/csvWriter.py
pyarchimate-0.9.66.dist-info/licenses/LICENSE
pyarchimate-0.9.66.dist-info/METADATA
pyarchimate-0.9.66.dist-info/WHEEL
pyarchimate-0.9.66.dist-info/top_level.txt
pyarchimate-0.9.66.dist-info/zip-safe
pyarchimate-0.9.66.dist-info/RECORD
