Metadata-Version: 2.4
Name: pyArchimate
Version: 0.9.66
Summary: A library to create & manage Archimate files
Author-email: Xavier Mayeur <xavier@mayeur.be>
Project-URL: Homepage, https://github.com/pyArchimate/pyArchimate
Project-URL: Bug Tracker, https://github.com/pyArchimate/pyArchimate/issues
Classifier: Programming Language :: Python :: 3
Classifier: License :: OSI Approved :: MIT License
Classifier: Operating System :: OS Independent
Requires-Python: >=3.7
License-File: LICENSE
Requires-Dist: lxml
Requires-Dist: oyaml
Requires-Dist: pillow
Dynamic: license-file
